[{"CandidateName":"महेश बस्नेत","Gender":"पुरुष","Age":62,"PartyID":0,"SymbolID":2,"SymbolName":"सूर्य","CandidateID":333899,"StateName":"प्रदेश १","PoliticalPartyName":"नेपाल कम्युनिष्ट पार्टी (एमाले)","ElectionPost":null,"DistrictCd":3,"DistrictName":"इलाम","State":1,"SCConstID":"1","CenterConstID":null,"SerialNo":27,"TotalVoteReceived":25753,"CastedVote":0,"TotalVoters":0,"Rank":"1","Remarks":"Elected","Samudaya":null,"DOB":"2017.05.16","CTZDIST":"इलाम","FATHER_NAME":"पदम बहादुर बस्नेत","SPOUCE_NAME":"कुन्ति  गुरुङ्ग","QUALIFICATION":"Bachelor","EXPERIENCE":"","OTHERDETAILS":"","NAMEOFINST":"","ADDRESS":"इलाम इलाम नगरपालिका भानुपथ"},{"CandidateName":"झलनाथ खनाल","Gender":"पुरुष","Age":72,"PartyID":0,"SymbolID":1020,"SymbolName":"कलम","CandidateID":335202,"StateName":"प्रदेश १","PoliticalPartyName":"नेपाल कम्युनिष्ट पार्टी (एकिकृत समाजबादी) ","ElectionPost":null,"DistrictCd":3,"DistrictName":"इलाम","State":1,"SCConstID":"1","CenterConstID":null,"SerialNo":28,"TotalVoteReceived":23089,"CastedVote":0,"TotalVoters":0,"Rank":"1","Remarks":null,"Samudaya":null,"DOB":"2006.12.06","CTZDIST":"इलाम","FATHER_NAME":"पुंग नाथ खनाल","SPOUCE_NAME":"रवी लक्ष्मी चित्रकार","QUALIFICATION":"Bachelor","EXPERIENCE":"","OTHERDETAILS":"","NAMEOFINST":"","ADDRESS":"इलाम सूर्योदय नगरपालिका "},{"CandidateName":"बुद्ध लाल मेचे","Gender":"पुरुष","Age":52,"PartyID":0,"SymbolID":35,"SymbolName":"कुखुराको भाले","CandidateID":333778,"StateName":"प्रदेश १","PoliticalPartyName":"मंगोल नेशनल अर्गनाइजेसन","ElectionPost":null,"DistrictCd":3,"DistrictName":"इलाम","State":1,"SCConstID":"1","CenterConstID":null,"SerialNo":29,"TotalVoteReceived":2442,"CastedVote":0,"TotalVoters":0,"Rank":"1","Remarks":null,"Samudaya":null,"DOB":"2027.02.09","CTZDIST":"झापा","FATHER_NAME":"सतालु  मेचे","SPOUCE_NAME":"छिन्ता  मेचे","QUALIFICATION":"Education N/A","EXPERIENCE":"","OTHERDETAILS":"","NAMEOFINST":"","ADDRESS":"झापा मेची नगर नगरपालिका वडाखाल"},{"CandidateName":"तोया नाथ शर्मा सापकोटा","Gender":"पुरुष","Age":67,"PartyID":0,"SymbolID":2279,"SymbolName":"हलो","CandidateID":333508,"StateName":"प्रदेश १","PoliticalPartyName":"राष्ट्रिय प्रजातन्त्र पार्टी","ElectionPost":null,"DistrictCd":3,"DistrictName":"इलाम","State":1,"SCConstID":"1","CenterConstID":null,"SerialNo":30,"TotalVoteReceived":1599,"CastedVote":0,"TotalVoters":0,"Rank":"1","Remarks":null,"Samudaya":null,"DOB":"2011.10.29","CTZDIST":"इलाम","FATHER_NAME":"लक्ष्मी प्रसाद सापकोटा","SPOUCE_NAME":"बेनु माया सापकोटा","QUALIFICATION":"Masters","EXPERIENCE":"","OTHERDETAILS":"","NAMEOFINST":"त्रि बि बि नेपाल","ADDRESS":"इलाम सूर्योदय नगरपालिका छिपिटार"},{"CandidateName":"कमल कुमार राई","Gender":"पुरुष","Age":63,"PartyID":0,"SymbolID":2278,"SymbolName":"ढल्केको छाता","CandidateID":334835,"StateName":"प्रदेश १","PoliticalPartyName":"जनता समाजवादी पार्टी, नेपाल ","ElectionPost":null,"DistrictCd":3,"DistrictName":"इलाम","State":1,"SCConstID":"1","CenterConstID":null,"SerialNo":31,"TotalVoteReceived":1313,"CastedVote":0,"TotalVoters":0,"Rank":"1","Remarks":null,"Samudaya":null,"DOB":"2015.10.12","CTZDIST":"इलाम","FATHER_NAME":"धन मान राई","SPOUCE_NAME":"कर्ण कुमारी राई","QUALIFICATION":"UNDER SLC","EXPERIENCE":"","OTHERDETAILS":"","NAMEOFINST":"","ADDRESS":"इलाम सूर्योदय नगरपालिका आहाले"},{"CandidateName":"बिक्रम पाण्डे","Gender":"पुरुष","Age":68,"PartyID":0,"SymbolID":54,"SymbolName":"माछा","CandidateID":333688,"StateName":"प्रदेश १","PoliticalPartyName":"स्वतन्त्र","ElectionPost":null,"DistrictCd":3,"DistrictName":"इलाम","State":1,"SCConstID":"1","CenterConstID":null,"SerialNo":32,"TotalVoteReceived":1184,"CastedVote":0,"TotalVoters":0,"Rank":"1","Remarks":null,"Samudaya":null,"DOB":"2010.09.24","CTZDIST":"इलाम","FATHER_NAME":"लाल बहादुर पाण्डे","SPOUCE_NAME":"माला  पाण्डे","QUALIFICATION":"Bachelor","EXPERIENCE":"","OTHERDETAILS":"","NAMEOFINST":"","ADDRESS":"इलाम सूर्योदय नगरपालिका बागबिरे"},{"CandidateName":"निमा तेन्जीङ शेर्पा","Gender":"पुरुष","Age":57,"PartyID":0,"SymbolID":2462,"SymbolName":"क्रस खुकुरी","CandidateID":333401,"StateName":"प्रदेश १","PoliticalPartyName":"स्वतन्त्र","ElectionPost":null,"DistrictCd":3,"DistrictName":"इलाम","State":1,"SCConstID":"1","CenterConstID":null,"SerialNo":33,"TotalVoteReceived":640,"CastedVote":0,"TotalVoters":0,"Rank":"1","Remarks":null,"Samudaya":null,"DOB":"2022.02.05","CTZDIST":"इलाम","FATHER_NAME":"दावा  शेर्पा","SPOUCE_NAME":"मुक्ता बास्कोटा शेर्पा","QUALIFICATION":"Masters","EXPERIENCE":"","OTHERDETAILS":"","NAMEOFINST":"","ADDRESS":"इलाम सूर्योदय नगरपालिका "},{"CandidateName":"गणेस प्रसाद पौडेल","Gender":"पुरुष","Age":60,"PartyID":0,"SymbolID":86,"SymbolName":"करुवा","CandidateID":333357,"StateName":"प्रदेश १","PoliticalPartyName":"नेपाली कांग्रेस (बी.पी.)","ElectionPost":null,"DistrictCd":3,"DistrictName":"इलाम","State":1,"SCConstID":"1","CenterConstID":null,"SerialNo":34,"TotalVoteReceived":347,"CastedVote":0,"TotalVoters":0,"Rank":"1","Remarks":null,"Samudaya":null,"DOB":"2018.07.14","CTZDIST":"इलाम","FATHER_NAME":"काशी नाथ पौडेल","SPOUCE_NAME":"ईश्वरा देबी पौडेल","QUALIFICATION":"Bachelor","EXPERIENCE":"३६ बर्ष शिक्षण\nसमाजसेवा\nने शि. संघमा काम गरेको ","OTHERDETAILS":"","NAMEOFINST":"त्रि बि बि","ADDRESS":"इलाम सूर्योदय नगरपालिका बतासे"},{"CandidateName":"पदम बहादुर लिम्बु","Gender":"पुरुष","Age":49,"PartyID":0,"SymbolID":13,"SymbolName":"घर","CandidateID":333299,"StateName":"प्रदेश १","PoliticalPartyName":"राष्ट्रिय जनमुक्ति पार्टी","ElectionPost":null,"DistrictCd":3,"DistrictName":"इलाम","State":1,"SCConstID":"1","CenterConstID":null,"SerialNo":35,"TotalVoteReceived":265,"CastedVote":0,"TotalVoters":0,"Rank":"1","Remarks":null,"Samudaya":null,"DOB":"2030.02.05","CTZDIST":"मोरङ्ग","FATHER_NAME":"पूर्ण बहादुर लिम्बु","SPOUCE_NAME":"सञ्च कुमारी लिम्बु","QUALIFICATION":"SLC","EXPERIENCE":"","OTHERDETAILS":"","NAMEOFINST":"भानु मा.बि.","ADDRESS":"मोरङ्ग केरावारी गाउँपालिका वरगाछी"},{"CandidateName":"नेत्र प्रसाद रेग्मी","Gender":"पुरुष","Age":51,"PartyID":0,"SymbolID":315,"SymbolName":"मुढा","CandidateID":335916,"StateName":"प्रदेश १","PoliticalPartyName":"स्वतन्त्र","ElectionPost":null,"DistrictCd":3,"DistrictName":"इलाम","State":1,"SCConstID":"1","CenterConstID":null,"SerialNo":36,"TotalVoteReceived":235,"CastedVote":0,"TotalVoters":0,"Rank":"1","Remarks":null,"Samudaya":null,"DOB":"2027.10.05","CTZDIST":"इलाम","FATHER_NAME":"ट‌क नाथ रेग्मी","SPOUCE_NAME":"इर्षना  रेग्मी","QUALIFICATION":"Proficiency Certificate","EXPERIENCE":"","OTHERDETAILS":"","NAMEOFINST":"","ADDRESS":"इलाम सूर्योदय नगरपालिका दामसिंह"},{"CandidateName":"जीत कुमार मुखिया","Gender":"पुरुष","Age":50,"PartyID":0,"SymbolID":56,"SymbolName":"दाप सहितको खुकुरी","CandidateID":337709,"StateName":"प्रदेश १","PoliticalPartyName":"संघीय लोकतान्त्रिक राष्ट्रिय मञ्च","ElectionPost":null,"DistrictCd":3,"DistrictName":"इलाम","State":1,"SCConstID":"1","CenterConstID":null,"SerialNo":37,"TotalVoteReceived":151,"CastedVote":0,"TotalVoters":0,"Rank":"1","Remarks":null,"Samudaya":null,"DOB":"2029.06.14","CTZDIST":"इलाम","FATHER_NAME":"सुर्य बहादुर मुखिया","SPOUCE_NAME":"चन्द्र कुमारी मुखिया","QUALIFICATION":"Proficiency Certificate","EXPERIENCE":"","OTHERDETAILS":"","NAMEOFINST":"","ADDRESS":"इलाम इलाम नगरपालिका सुम्बेक"}]