[{"CandidateName":"दिपक खड्का","Gender":"पुरुष","Age":51,"PartyID":0,"SymbolID":1,"SymbolName":"रुख","CandidateID":335572,"StateName":"प्रदेश १","PoliticalPartyName":"नेपाली काँग्रेस","ElectionPost":null,"DistrictCd":5,"DistrictName":"संखुवासभा","State":1,"SCConstID":"1","CenterConstID":null,"SerialNo":146,"TotalVoteReceived":32161,"CastedVote":0,"TotalVoters":0,"Rank":"1","Remarks":"Elected","Samudaya":null,"DOB":"2028.03.15","CTZDIST":"संखुवासभा","FATHER_NAME":"द्रोण बहादुर खड्का","SPOUCE_NAME":"विनिता  खड्का","QUALIFICATION":"स्नातकोत्तर","EXPERIENCE":"","OTHERDETAILS":"","NAMEOFINST":"त्रिभुवन विश्वविद्यालय","ADDRESS":"संखुवासभा धर्मदेवी नगरपालिका जागिर गाउँ"},{"CandidateName":"राजेन्द्र प्रसाद गौत्तम","Gender":"पुरुष","Age":59,"PartyID":0,"SymbolID":2,"SymbolName":"सूर्य","CandidateID":335908,"StateName":"प्रदेश १","PoliticalPartyName":"नेपाल कम्युनिष्ट पार्टी (एमाले)","ElectionPost":null,"DistrictCd":5,"DistrictName":"संखुवासभा","State":1,"SCConstID":"1","CenterConstID":null,"SerialNo":147,"TotalVoteReceived":26721,"CastedVote":0,"TotalVoters":0,"Rank":"1","Remarks":null,"Samudaya":null,"DOB":"2019.09.05","CTZDIST":"संखुवासभा","FATHER_NAME":"नेत्र प्रसाद गौत्तम","SPOUCE_NAME":"बुद्धिमता  गौत्तम","QUALIFICATION":"एम.वि.ए.","EXPERIENCE":"निवर्तमान प्रतिनिधि सभा सदस्य भई काम गरेको\nप्रतिनिधि सभाको सार्वजनिक लेखा समितिको सदस्य","OTHERDETAILS":"नेकपा एमाले स्थायी समिति सदस्य 2065 सालदेखि केन्द्रीय नेतृत्वमा रही कार्य गरेको अवस्था छ।","NAMEOFINST":"पव्लिक युथ क्याम्पस","ADDRESS":"संखुवासभा चैनपुर नगरपालिका फलाटे गाउँ"},{"CandidateName":"भक्त नारायण श्रेष्ठ","Gender":"पुरुष","Age":55,"PartyID":0,"SymbolID":2445,"SymbolName":"गोलाकार भित्र घण्टी","CandidateID":334481,"StateName":"प्रदेश १","PoliticalPartyName":"राष्ट्रिय स्वतन्त्र पार्टी","ElectionPost":null,"DistrictCd":5,"DistrictName":"संखुवासभा","State":1,"SCConstID":"1","CenterConstID":null,"SerialNo":148,"TotalVoteReceived":1136,"CastedVote":0,"TotalVoters":0,"Rank":"1","Remarks":null,"Samudaya":null,"DOB":"2024.06.23","CTZDIST":"संखुवासभा","FATHER_NAME":"मान बहादुर श्रेष्ठ","SPOUCE_NAME":"इन्द्र कुमारी श्रेष्ठ","QUALIFICATION":"S.L.C.","EXPERIENCE":"1. अवकास प्राप्‍त नेपाल आर्मी\n2. प्रवासी नेपाली समन्वय सदस्य\n3. विभिन्‍न टोल/संस्थाको अध्यक्ष/सदस्य\n4. हाल सुप्रिम ह्युमन रिसोर्सको कार्यकारी प्रमुख\n","OTHERDETAILS":"राजनैतिकको कारणले गर्दा देशमा अस्थिरता भई व्यक्तिबाद स्वार्थवादले गिजलिएर अत्यन्त कष्टकर जीवनयापन जनजिविका भएको सबैमा अवगत नै छ। त्यसकारण देशमा सुसासन र भ्रष्टचार मुक्त गरी स्थायित्व सरकार संचालन गर्न जनचाहनाको अपेक्षा पुरा गर्न जिल्ला र राष्ट्रको लागि मेरो उम्मेदवारी पेस गर्दछु।","NAMEOFINST":"अम्बर सैनिक वोर्डिङ स्कुल छाउनी काठमाडौं","ADDRESS":"संखुवासभा खाँदवारी नगरपालिका धापासी"},{"CandidateName":"दिपक कुमार राई (याक्खा)","Gender":"पुरुष","Age":45,"PartyID":0,"SymbolID":2278,"SymbolName":"ढल्केको छाता","CandidateID":336818,"StateName":"प्रदेश १","PoliticalPartyName":"जनता समाजवादी पार्टी, नेपाल ","ElectionPost":null,"DistrictCd":5,"DistrictName":"संखुवासभा","State":1,"SCConstID":"1","CenterConstID":null,"SerialNo":149,"TotalVoteReceived":811,"CastedVote":0,"TotalVoters":0,"Rank":"1","Remarks":null,"Samudaya":null,"DOB":"2034.03.04","CTZDIST":"संखुवासभा","FATHER_NAME":"कृष्‍ण प्रसाद राई ","SPOUCE_NAME":"अञ्जना  राई","QUALIFICATION":"एम.ए","EXPERIENCE":"१७ वर्ष राजनीतिक\nसामाजिक अभियान","OTHERDETAILS":"","NAMEOFINST":"त्रि.वि.","ADDRESS":"संखुवासभा चैनपुर नगरपालिका चापाभुई"},{"CandidateName":"तेन्जी भोटिया","Gender":"पुरुष","Age":33,"PartyID":0,"SymbolID":54,"SymbolName":"माछा","CandidateID":335669,"StateName":"प्रदेश १","PoliticalPartyName":"स्वतन्त्र","ElectionPost":null,"DistrictCd":5,"DistrictName":"संखुवासभा","State":1,"SCConstID":"1","CenterConstID":null,"SerialNo":150,"TotalVoteReceived":532,"CastedVote":0,"TotalVoters":0,"Rank":"1","Remarks":null,"Samudaya":null,"DOB":"2046.04.17","CTZDIST":"इलाम","FATHER_NAME":"टाक ड्वाङ भोटिया","SPOUCE_NAME":"-","QUALIFICATION":"स्नाकोत्तर","EXPERIENCE":"शिक्षक-10 वर्ष\nपत्रकार - 3 वर्ष्\nसंगीतकर्मी - 6 वर्ष","OTHERDETAILS":"","NAMEOFINST":"सर्वपली राधाकृष्ण महाविद्यालय","ADDRESS":"इलाम सूर्योदय नगरपालिका मानेभन्ज्याङ"},{"CandidateName":"देवेन्द्र कुमार (रिल्ली) घले","Gender":"पुरुष","Age":55,"PartyID":0,"SymbolID":35,"SymbolName":"कुखुराको भाले","CandidateID":335500,"StateName":"प्रदेश १","PoliticalPartyName":"मंगोल नेशनल अर्गनाइजेसन","ElectionPost":null,"DistrictCd":5,"DistrictName":"संखुवासभा","State":1,"SCConstID":"1","CenterConstID":null,"SerialNo":151,"TotalVoteReceived":422,"CastedVote":0,"TotalVoters":0,"Rank":"1","Remarks":null,"Samudaya":null,"DOB":"2023.09.26","CTZDIST":"संखुवासभा","FATHER_NAME":"शन्त वीर घले","SPOUCE_NAME":"दिल माया गुरुङ","QUALIFICATION":"","EXPERIENCE":"","OTHERDETAILS":"","NAMEOFINST":"","ADDRESS":"संखुवासभा चिचिला गाउँपालिका बागसिदा"},{"CandidateName":"भोला मान कार्की","Gender":"पुरुष","Age":51,"PartyID":0,"SymbolID":2279,"SymbolName":"हलो","CandidateID":337913,"StateName":"प्रदेश १","PoliticalPartyName":"राष्ट्रिय प्रजातन्त्र पार्टी","ElectionPost":null,"DistrictCd":5,"DistrictName":"संखुवासभा","State":1,"SCConstID":"1","CenterConstID":null,"SerialNo":152,"TotalVoteReceived":308,"CastedVote":0,"TotalVoters":0,"Rank":"1","Remarks":null,"Samudaya":null,"DOB":"2028.03.13","CTZDIST":"संखुवासभा","FATHER_NAME":"बल बहालदुर कार्की","SPOUCE_NAME":"सृजना  कार्की","QUALIFICATION":"आइ.एल.","EXPERIENCE":"कृषि सम्बन्धि तालिम तथा गोष्ठी मा सहभागी भै हाल उखु खेती तथा प्रशोधन गरी सखर उत्पादन गर्ने कार्य गरिरहेको","OTHERDETAILS":"सङ्‍खुवासभा जिल्लामा समाज सेवा गर्दै उखु अदुवा अम्लिसो जस्ता आयमूलक कृषि उत्पादनमा जिल्ला वगासी लाई अभिप्रेरित गरी आर्थिक सम्बृद्धि तर्फ उन्मुख गराउन","NAMEOFINST":"जनता कानून क्याम्पस","ADDRESS":"मोरङ्ग विराटनगर महानगरपालिका अल्काटोल"},{"CandidateName":"टिका राम शाही","Gender":"पुरुष","Age":79,"PartyID":0,"SymbolID":2332,"SymbolName":"तीर","CandidateID":335397,"StateName":"प्रदेश १","PoliticalPartyName":"राष्ट्रिय प्रजातन्त्र पार्टी नेपाल","ElectionPost":null,"DistrictCd":5,"DistrictName":"संखुवासभा","State":1,"SCConstID":"1","CenterConstID":null,"SerialNo":153,"TotalVoteReceived":152,"CastedVote":0,"TotalVoters":0,"Rank":"1","Remarks":null,"Samudaya":null,"DOB":"1999.07.22","CTZDIST":"संखुवासभा","FATHER_NAME":"हस्त बहादुर शाही","SPOUCE_NAME":"चन्दीका देवी शाही","QUALIFICATION":"S.L.C.","EXPERIENCE":"","OTHERDETAILS":"","NAMEOFINST":"तेह्रथुम माध्यमिक विद्यालय","ADDRESS":"संखुवासभा चैनपुर नगरपालिका तेर्सो लाइन"},{"CandidateName":"राज कुमार लिम्बु","Gender":"पुरुष","Age":35,"PartyID":0,"SymbolID":56,"SymbolName":"दाप सहितको खुकुरी","CandidateID":336925,"StateName":"प्रदेश १","PoliticalPartyName":"संघीय लोकतान्त्रिक राष्ट्रिय मञ्च","ElectionPost":null,"DistrictCd":5,"DistrictName":"संखुवासभा","State":1,"SCConstID":"1","CenterConstID":null,"SerialNo":154,"TotalVoteReceived":139,"CastedVote":0,"TotalVoters":0,"Rank":"1","Remarks":null,"Samudaya":null,"DOB":"2043.10.10","CTZDIST":"संखुवासभा","FATHER_NAME":"मीन बहादुर लिम्बु","SPOUCE_NAME":"-","QUALIFICATION":"Proficiency Certificate","EXPERIENCE":"","OTHERDETAILS":"संघीय लोकतान्त्रीक गणतान्त्रिक धर्मनिरपेेक्ष राष्ट्रिय नेपाललालई संस्थागत","NAMEOFINST":"पशुपति बहुमुखी क्याम्पस","ADDRESS":"संखुवासभा चैनपुर नगरपालिका सिङजोङग"},{"CandidateName":"प्रविन कार्की","Gender":"पुरुष","Age":30,"PartyID":0,"SymbolID":2462,"SymbolName":"क्रस खुकुरी","CandidateID":334084,"StateName":"प्रदेश १","PoliticalPartyName":"स्वतन्त्र","ElectionPost":null,"DistrictCd":5,"DistrictName":"संखुवासभा","State":1,"SCConstID":"1","CenterConstID":null,"SerialNo":155,"TotalVoteReceived":131,"CastedVote":0,"TotalVoters":0,"Rank":"1","Remarks":null,"Samudaya":null,"DOB":"2049.06.18","CTZDIST":"संखुवासभा","FATHER_NAME":"रेख बहादुर कार्की","SPOUCE_NAME":"-","QUALIFICATION":"I.A.","EXPERIENCE":"","OTHERDETAILS":"","NAMEOFINST":"श्री हिमालय किरण पब्लिक क्याम्पस","ADDRESS":"संखुवासभा खाँदवारी नगरपालिका गुवाबारी"},{"CandidateName":"कृष्ण कुमार राई(कुलुङ)","Gender":"पुरुष","Age":65,"PartyID":0,"SymbolID":13,"SymbolName":"घर","CandidateID":335019,"StateName":"प्रदेश १","PoliticalPartyName":"राष्ट्रिय जनमुक्ति पार्टी","ElectionPost":null,"DistrictCd":5,"DistrictName":"संखुवासभा","State":1,"SCConstID":"1","CenterConstID":null,"SerialNo":156,"TotalVoteReceived":46,"CastedVote":0,"TotalVoters":0,"Rank":"1","Remarks":null,"Samudaya":null,"DOB":"2014.05.13","CTZDIST":"संखुवासभा","FATHER_NAME":"हस्त धन राई(कुलुङ)","SPOUCE_NAME":"सहिन्द्रा कुमारी राई(कुलुङ)","QUALIFICATION":"सामान्य","EXPERIENCE":"","OTHERDETAILS":"","NAMEOFINST":"","ADDRESS":"संखुवासभा सिलीचोङ गाउँपालिका तेन्छोङ"},{"CandidateName":"बिनोद घिमिरे","Gender":"पुरुष","Age":60,"PartyID":0,"SymbolID":1026,"SymbolName":"लाटोकोसेरो","CandidateID":338366,"StateName":"प्रदेश १","PoliticalPartyName":"नेश्नलिष्ट पिपल्स पार्टी","ElectionPost":null,"DistrictCd":5,"DistrictName":"संखुवासभा","State":1,"SCConstID":"1","CenterConstID":null,"SerialNo":157,"TotalVoteReceived":26,"CastedVote":0,"TotalVoters":0,"Rank":"1","Remarks":null,"Samudaya":null,"DOB":"2019.12.25","CTZDIST":"संखुवासभा","FATHER_NAME":"टेकनाथ  घिमिरे","SPOUCE_NAME":"पुष्पा  भण्डारी (घिमिरे)","QUALIFICATION":"एस.एल.सी","EXPERIENCE":"","OTHERDETAILS":"","NAMEOFINST":"श्री शारदा मा.वि. स्याउली","ADDRESS":"संखुवासभा खाँदवारी नगरपालिका रेडक्रस मार्ग"}]